sopel_bsky/__init__.py
sopel_bsky/plugin.py
sopel_bsky-0.1.2.dist-info/licenses/COPYING
sopel_bsky-0.1.2.dist-info/METADATA
sopel_bsky-0.1.2.dist-info/WHEEL
sopel_bsky-0.1.2.dist-info/entry_points.txt
sopel_bsky-0.1.2.dist-info/top_level.txt
sopel_bsky-0.1.2.dist-info/RECORD
