Metadata-Version: 2.4
Name: sopel-bsky
Version: 0.1.2
Summary: Fetch info about Bluesky links in your IRC conversations using Sopel.
Author-email: dgw <dgw@technobabbl.es>
License-Expression: EFL-2.0
Project-URL: Homepage, https://github.com/dgw/sopel-bsky
Project-URL: Bug Tracker, https://github.com/dgw/sopel-bsky/issues
Keywords: sopel,plugin,bot,irc
Platform: Linux x86, x86-64
Classifier: Development Status :: 4 - Beta
Classifier: Intended Audience :: Developers
Classifier: Intended Audience :: System Administrators
Classifier: Topic :: Communications :: Chat :: Internet Relay Chat
Requires-Python: <3.14,>=3.8
License-File: COPYING
Requires-Dist: sopel>=8.0
Requires-Dist: atproto==0.0.62
Dynamic: license-file
